smallpebble/__init__.py
smallpebble/datasets.py
smallpebble/gradcheck.py
smallpebble/smallpebble.py
smallpebble-3.0.5.dist-info/METADATA
smallpebble-3.0.5.dist-info/WHEEL
smallpebble-3.0.5.dist-info/licenses/LICENSE
smallpebble-3.0.5.dist-info/RECORD
