Metadata-Version: 2.4
Name: smallpebble
Version: 3.0.5
Summary: A minimalist deep learning library written from scratch in Python
Project-URL: Homepage, https://github.com/sradc/smallpebble
Project-URL: Repository, https://github.com/sradc/smallpebble
Author-email: Sidney Radcliffe <sidneyradcliffe@gmail.com>
License-Expression: Apache-2.0
License-File: LICENSE
Classifier: Operating System :: OS Independent
Classifier: Programming Language :: Python :: 3
Requires-Python: >=3.10
Requires-Dist: numpy>=1.24.0
Provides-Extra: examples
Requires-Dist: ipykernel>=7.1.0; extra == 'examples'
Requires-Dist: matplotlib>=3.10.8; extra == 'examples'
Requires-Dist: requests>=2.32.5; extra == 'examples'
Requires-Dist: tqdm>=4.67.1; extra == 'examples'
